[{"ratings": [85, 60, 120], "rankings": [2, 3, 1], "batch": 0, "ratingTime": 17094, "groundtruth": [69, 71, 78], "frames": 3, "rankingTime": 16747}, {"ratings": [50, 92, 60, 85, 80, 65], "rankings": [5, 3, 6, 1, 2, 4], "batch": 0, "ratingTime": 87611, "groundtruth": [52, 55, 63, 65, 66, 68], "frames": 6, "rankingTime": 6271}, {"ratings": [60, 45], "rankings": [2, 1], "batch": 0, "ratingTime": 5751, "groundtruth": [55, 62], "frames": 2, "rankingTime": 3655}, {"ratings": [35, 60, 40, 85, 60], "rankings": [4, 2, 3, 5, 1], "batch": 0, "ratingTime": 22007, "groundtruth": [50, 54, 58, 66, 75], "frames": 5, "rankingTime": 4062}, {"ratings": [56, 66], "rankings": [1, 2], "batch": 0, "ratingTime": 65167, "groundtruth": [57, 77], "frames": 2, "rankingTime": 31259}, {"ratings": [65, 58, 72], "rankings": [1, 3, 2], "batch": 0, "ratingTime": 19154, "groundtruth": [50, 53, 68], "frames": 3, "rankingTime": 11960}, {"ratings": [56, 58, 62, 75, 53], "rankings": [5, 3, 4, 1, 2], "batch": 0, "ratingTime": 18169, "groundtruth": [51, 56, 59, 65, 70], "frames": 5, "rankingTime": 8129}, {"ratings": [66, 65, 65, 78, 76, 56], "rankings": [4, 1, 6, 3, 5, 2], "batch": 0, "ratingTime": 22149, "groundtruth": [50, 57, 58, 74, 75, 77], "frames": 6, "rankingTime": 5485}, {"ratings": [25, 44, 62], "rankings": [3, 1, 2], "batch": 0, "ratingTime": 11700, "groundtruth": [57, 73, 76], "frames": 3, "rankingTime": 14900}, {"ratings": [33, 25], "rankings": [2, 1], "batch": 0, "ratingTime": 11415, "groundtruth": [51, 52], "frames": 2, "rankingTime": 7032}, {"ratings": [35, 24, 39, 52, 36, 45], "rankings": [5, 6, 3, 1, 4, 2], "batch": 0, "ratingTime": 27229, "groundtruth": [53, 62, 67, 72, 78, 79], "frames": 6, "rankingTime": 10424}, {"ratings": [25, 54, 48, 44, 56], "rankings": [4, 2, 3, 1, 5], "batch": 0, "ratingTime": 21186, "groundtruth": [61, 68, 69, 72, 77], "frames": 5, "rankingTime": 16433}, {"ratings": [70, 125], "rankings": [2, 1], "batch": 0, "ratingTime": 23965, "groundtruth": [66, 78], "frames": 2, "rankingTime": 17718}, {"ratings": [73, 59, 112, 115, 90, 138], "rankings": [6, 3, 1, 5, 4, 2], "batch": 1, "ratingTime": 39431, "groundtruth": [52, 59, 61, 65, 73, 77], "frames": 6, "rankingTime": 28541}, {"ratings": [125, 127, 103], "rankings": [2, 1, 3], "batch": 0, "ratingTime": 21401, "groundtruth": [70, 72, 75], "frames": 3, "rankingTime": 12444}, {"ratings": [65, 92, 97, 88, 79], "rankings": [4, 3, 2, 5, 1], "batch": 1, "ratingTime": 29863, "groundtruth": [71, 72, 73, 75, 76], "frames": 5, "rankingTime": 14239}, {"ratings": [30, 35, 55], "rankings": [3, 2, 1], "batch": 0, "ratingTime": 38487, "groundtruth": [59, 62, 64], "frames": 3, "rankingTime": 19015}, {"ratings": [40, 45, 55, 52, 60], "rankings": [5, 4, 3, 2, 1], "batch": 1, "ratingTime": 57651, "groundtruth": [51, 52, 66, 77, 79], "frames": 5, "rankingTime": 22747}, {"ratings": [48, 50, 50, 58, 56, 60], "rankings": [5, 6, 3, 4, 2, 1], "batch": 1, "ratingTime": 43793, "groundtruth": [50, 56, 64, 67, 72, 75], "frames": 6, "rankingTime": 32463}, {"ratings": [50, 75], "rankings": [2, 1], "batch": 0, "ratingTime": 26483, "groundtruth": [64, 76], "frames": 2, "rankingTime": 4599}, {"ratings": [45, 55, 50, 78, 60], "rankings": [4, 5, 3, 1, 2], "batch": 1, "ratingTime": 75615, "groundtruth": [55, 57, 61, 67, 70], "frames": 5, "rankingTime": 54237}, {"ratings": [46, 45, 60, 55, 65, 75], "rankings": [6, 5, 4, 2, 3, 1], "batch": 1, "ratingTime": 78449, "groundtruth": [57, 58, 60, 70, 74, 78], "frames": 6, "rankingTime": 48510}, {"ratings": [46, 55], "rankings": [2, 1], "batch": 0, "ratingTime": 22068, "groundtruth": [54, 65], "frames": 2, "rankingTime": 8534}, {"ratings": [46, 63, 60], "rankings": [3, 2, 1], "batch": 0, "ratingTime": 31400, "groundtruth": [52, 56, 65], "frames": 3, "rankingTime": 18190}, {"ratings": [60, 65, 70], "rankings": [2, 3, 1], "batch": 1, "ratingTime": 37048, "groundtruth": [63, 65, 75], "frames": 3, "rankingTime": 56189}, {"ratings": [45, 55, 50, 60, 55, 60], "rankings": [6, 5, 3, 4, 2, 1], "batch": 2, "ratingTime": 56041, "groundtruth": [50, 54, 58, 63, 65, 78], "frames": 6, "rankingTime": 41679}, {"ratings": [45, 60, 60, 65, 65], "rankings": [5, 3, 1, 4, 2], "batch": 1, "ratingTime": 48166, "groundtruth": [53, 62, 63, 65, 74], "frames": 5, "rankingTime": 18619}, {"ratings": [50, 55], "rankings": [1, 2], "batch": 0, "ratingTime": 21219, "groundtruth": [59, 63], "frames": 2, "rankingTime": 17587}, {"ratings": [45, 40, 35, 50, 55, 25], "rankings": [3, 6, 5, 4, 1, 2], "batch": 2, "ratingTime": 25153, "groundtruth": [55, 57, 64, 67, 70, 75], "frames": 6, "rankingTime": 7716}, {"ratings": [43, 30, 56, 35, 25], "rankings": [5, 3, 2, 4, 1], "batch": 1, "ratingTime": 19065, "groundtruth": [50, 59, 64, 69, 78], "frames": 5, "rankingTime": 5705}, {"ratings": [35, 42], "rankings": [2, 1], "batch": 0, "ratingTime": 17206, "groundtruth": [50, 79], "frames": 2, "rankingTime": 6593}, {"ratings": [26, 35, 30], "rankings": [2, 3, 1], "batch": 1, "ratingTime": 36078, "groundtruth": [53, 54, 67], "frames": 3, "rankingTime": 6142}, {"ratings": [30, 36, 40], "rankings": [3, 2, 1], "batch": 1, "ratingTime": 14347, "groundtruth": [51, 69, 79], "frames": 3, "rankingTime": 8978}, {"ratings": [33, 28], "rankings": [2, 1], "batch": 0, "ratingTime": 7335, "groundtruth": [71, 72], "frames": 2, "rankingTime": 4587}, {"ratings": [20, 25, 45, 32, 50, 40], "rankings": [6, 4, 5, 3, 1, 2], "batch": 2, "ratingTime": 14786, "groundtruth": [52, 56, 60, 62, 74, 77], "frames": 6, "rankingTime": 9547}, {"ratings": [20, 45, 30, 39, 35], "rankings": [1, 5, 3, 2, 4], "batch": 2, "ratingTime": 15692, "groundtruth": [66, 70, 74, 76, 77], "frames": 5, "rankingTime": 9591}, {"ratings": [48, 56, 50, 59, 60, 48], "rankings": [1, 2, 3, 4, 6, 5], "batch": 2, "ratingTime": 30150, "groundtruth": [59, 66, 68, 71, 73, 79], "frames": 6, "rankingTime": 18398}, {"ratings": [69, 65], "rankings": [2, 1], "batch": 0, "ratingTime": 5343, "groundtruth": [67, 69], "frames": 2, "rankingTime": 8274}, {"ratings": [65, 65, 65], "rankings": [3, 2, 1], "batch": 1, "ratingTime": 7171, "groundtruth": [60, 76, 77], "frames": 3, "rankingTime": 11190}, {"ratings": [69, 65, 70, 55, 68], "rankings": [1, 4, 5, 3, 2], "batch": 2, "ratingTime": 13624, "groundtruth": [50, 58, 72, 73, 79], "frames": 5, "rankingTime": 6564}, {"ratings": [51, 52, 62, 76, 72, 80], "rankings": [6, 4, 3, 5, 2, 1], "batch": 2, "ratingTime": 456189, "groundtruth": [51, 53, 61, 69, 72, 76], "frames": 6, "rankingTime": 196386}, {"ratings": [67, 66, 58], "rankings": [3, 1, 2], "batch": 1, "ratingTime": 212963, "groundtruth": [68, 73, 74], "frames": 3, "rankingTime": 46374}, {"ratings": [54, 52, 56, 61, 74], "rankings": [5, 4, 3, 2, 1], "batch": 2, "ratingTime": 490341, "groundtruth": [52, 53, 57, 65, 75], "frames": 5, "rankingTime": 25482}, {"ratings": [60, 67], "rankings": [2, 1], "batch": 0, "ratingTime": 26280, "groundtruth": [61, 73], "frames": 2, "rankingTime": 12220}, {"ratings": [53, 56, 60, 75, 79], "rankings": [5, 3, 4, 2, 1], "batch": 2, "ratingTime": 140727, "groundtruth": [51, 59, 60, 71, 78], "frames": 5, "rankingTime": 17866}, {"ratings": [59, 76, 70], "rankings": [3, 2, 1], "batch": 1, "ratingTime": 100791, "groundtruth": [59, 71, 78], "frames": 3, "rankingTime": 9172}, {"ratings": [53, 58, 70, 57, 72, 70], "rankings": [5, 6, 3, 4, 1, 2], "batch": 3, "ratingTime": 202291, "groundtruth": [52, 63, 67, 68, 72, 79], "frames": 6, "rankingTime": 22507}, {"ratings": [60, 65], "rankings": [1, 2], "batch": 1, "ratingTime": 62389, "groundtruth": [70, 76], "frames": 2, "rankingTime": 18397}, {"ratings": [50, 60, 100, 50, 100, 100], "rankings": [6, 5, 3, 4, 2, 1], "batch": 3, "ratingTime": 32727, "groundtruth": [53, 61, 66, 73, 77, 78], "frames": 6, "rankingTime": 31335}, {"ratings": [75, 100], "rankings": [1, 2], "batch": 1, "ratingTime": 5940, "groundtruth": [78, 79], "frames": 2, "rankingTime": 6522}, {"ratings": [50, 50, 50], "rankings": [3, 2, 1], "batch": 1, "ratingTime": 8242, "groundtruth": [55, 58, 66], "frames": 3, "rankingTime": 8259}, {"ratings": [50, 80, 100, 60, 70], "rankings": [3, 2, 1, 5, 4], "batch": 2, "ratingTime": 13152, "groundtruth": [54, 56, 62, 64, 67], "frames": 5, "rankingTime": 8101}, {"ratings": [75, 50], "rankings": [2, 1], "batch": 1, "ratingTime": 48294, "groundtruth": [59, 61], "frames": 2, "rankingTime": 26222}, {"ratings": [50, 50, 52, 80, 60], "rankings": [2, 4, 3, 5, 1], "batch": 2, "ratingTime": 96713, "groundtruth": [55, 61, 63, 68, 69], "frames": 5, "rankingTime": 86198}, {"ratings": [60, 60, 60, 60, 60, 65], "rankings": [4, 3, 1, 5, 2, 6], "batch": 3, "ratingTime": 122195, "groundtruth": [56, 57, 59, 64, 71, 76], "frames": 6, "rankingTime": 7552}, {"ratings": [40, 40, 40], "rankings": [2, 3, 1], "batch": 1, "ratingTime": 120352, "groundtruth": [50, 56, 62], "frames": 3, "rankingTime": 20289}, {"ratings": [49, 60, 80, 77, 55], "rankings": [5, 4, 3, 2, 1], "batch": 3, "ratingTime": 196707, "groundtruth": [52, 66, 76, 77, 78], "frames": 5, "rankingTime": 10850}, {"ratings": [35, 40, 40], "rankings": [2, 3, 1], "batch": 1, "ratingTime": 15586, "groundtruth": [57, 64, 70], "frames": 3, "rankingTime": 6571}, {"ratings": [30, 37], "rankings": [1, 2], "batch": 1, "ratingTime": 9984, "groundtruth": [66, 75], "frames": 2, "rankingTime": 4236}, {"ratings": [30, 30, 30, 30, 25, 30], "rankings": [1, 2, 6, 3, 5, 4], "batch": 3, "ratingTime": 46041, "groundtruth": [50, 51, 54, 55, 58, 74], "frames": 6, "rankingTime": 10113}, {"ratings": [80, 50, 90, 78, 89], "rankings": [4, 1, 2, 3, 5], "batch": 3, "ratingTime": 43010, "groundtruth": [57, 59, 69, 73, 79], "frames": 5, "rankingTime": 29931}, {"ratings": [60, 80, 99], "rankings": [3, 2, 1], "batch": 2, "ratingTime": 25190, "groundtruth": [58, 62, 77], "frames": 3, "rankingTime": 9115}, {"ratings": [50, 80, 75, 90, 99, 90], "rankings": [3, 2, 1, 6, 4, 5], "batch": 4, "ratingTime": 62200, "groundtruth": [50, 58, 63, 65, 71, 76], "frames": 6, "rankingTime": 5135}, {"ratings": [70, 70], "rankings": [1, 2], "batch": 1, "ratingTime": 12461, "groundtruth": [62, 64], "frames": 2, "rankingTime": 3547}, {"ratings": [49, 48, 39, 46, 38], "rankings": [4, 5, 2, 1, 3], "batch": 3, "ratingTime": 30650, "groundtruth": [53, 61, 63, 71, 72], "frames": 5, "rankingTime": 38330}, {"ratings": [40, 38, 30, 45, 37, 35], "rankings": [2, 6, 4, 5, 3, 1], "batch": 4, "ratingTime": 1458162, "groundtruth": [51, 54, 57, 61, 68, 79], "frames": 6, "rankingTime": 5820}, {"ratings": [37, 38, 50], "rankings": [1, 3, 2], "batch": 2, "ratingTime": 338161, "groundtruth": [67, 71, 72], "frames": 3, "rankingTime": 6236}, {"ratings": [29, 28], "rankings": [1, 2], "batch": 1, "ratingTime": 12889, "groundtruth": [56, 74], "frames": 2, "rankingTime": 10932}, {"ratings": [40, 55, 50], "rankings": [3, 1, 2], "batch": 2, "ratingTime": 42335, "groundtruth": [52, 66, 69], "frames": 3, "rankingTime": 29002}, {"ratings": [45, 60], "rankings": [2, 1], "batch": 1, "ratingTime": 20699, "groundtruth": [51, 72], "frames": 2, "rankingTime": 23889}, {"ratings": [43, 50, 40, 55, 55, 65], "rankings": [6, 5, 4, 2, 3, 1], "batch": 4, "ratingTime": 66396, "groundtruth": [53, 64, 66, 69, 74, 77], "frames": 6, "rankingTime": 96926}, {"ratings": [60, 62, 68, 50, 65], "rankings": [4, 2, 1, 5, 3], "batch": 3, "ratingTime": 58964, "groundtruth": [65, 67, 70, 74, 75], "frames": 5, "rankingTime": 69662}, {"ratings": [50, 60, 40], "rankings": [3, 1, 2], "batch": 2, "ratingTime": 19978, "groundtruth": [55, 56, 59], "frames": 3, "rankingTime": 41108}, {"ratings": [40, 45, 40, 60, 55], "rankings": [5, 4, 3, 1, 2], "batch": 3, "ratingTime": 33264, "groundtruth": [50, 51, 60, 62, 64], "frames": 5, "rankingTime": 17743}, {"ratings": [45, 40, 70, 55, 80, 65], "rankings": [6, 4, 5, 2, 1, 3], "batch": 4, "ratingTime": 28423, "groundtruth": [52, 55, 60, 67, 75, 78], "frames": 6, "rankingTime": 18315}, {"ratings": [55, 65], "rankings": [2, 1], "batch": 1, "ratingTime": 15327, "groundtruth": [55, 71], "frames": 2, "rankingTime": 9361}, {"ratings": [44, 55, 55, 66, 50, 66], "rankings": [5, 6, 3, 4, 2, 1], "batch": 4, "ratingTime": 45289, "groundtruth": [56, 59, 62, 70, 72, 73], "frames": 6, "rankingTime": 13211}, {"ratings": [60, 66, 65], "rankings": [3, 2, 1], "batch": 2, "ratingTime": 30702, "groundtruth": [53, 68, 78], "frames": 3, "rankingTime": 7686}, {"ratings": [40, 44], "rankings": [2, 1], "batch": 1, "ratingTime": 5684, "groundtruth": [53, 77], "frames": 2, "rankingTime": 5071}, {"ratings": [55, 66, 60, 55, 60], "rankings": [5, 4, 2, 1, 3], "batch": 4, "ratingTime": 21539, "groundtruth": [56, 60, 65, 69, 79], "frames": 5, "rankingTime": 8473}, {"ratings": [52, 80, 75], "rankings": [3, 2, 1], "batch": 2, "ratingTime": 75810, "groundtruth": [50, 75, 76], "frames": 3, "rankingTime": 37441}, {"ratings": [54, 60], "rankings": [2, 1], "batch": 1, "ratingTime": 23890, "groundtruth": [58, 63], "frames": 2, "rankingTime": 52462}, {"ratings": [65, 56, 70, 62, 60], "rankings": [5, 2, 3, 4, 1], "batch": 4, "ratingTime": 100051, "groundtruth": [52, 55, 57, 59, 67], "frames": 5, "rankingTime": 24738}, {"ratings": [51, 50, 50, 70, 60, 60], "rankings": [6, 3, 5, 4, 2, 1], "batch": 5, "ratingTime": 112601, "groundtruth": [55, 61, 64, 65, 69, 72], "frames": 6, "rankingTime": 50784}, {"ratings": [28, 55], "rankings": [2, 1], "batch": 1, "ratingTime": 8288, "groundtruth": [50, 69], "frames": 2, "rankingTime": 20476}, {"ratings": [55, 25, 40, 35, 28], "rankings": [5, 4, 2, 1, 3], "batch": 4, "ratingTime": 24341, "groundtruth": [53, 61, 71, 73, 77], "frames": 5, "rankingTime": 29726}, {"ratings": [30, 28, 25], "rankings": [3, 2, 1], "batch": 2, "ratingTime": 7808, "groundtruth": [51, 63, 64], "frames": 3, "rankingTime": 8287}, {"ratings": [35, 30, 42, 23, 38, 25], "rankings": [5, 6, 3, 4, 2, 1], "batch": 5, "ratingTime": 16360, "groundtruth": [50, 51, 52, 53, 57, 66], "frames": 6, "rankingTime": 12671}, {"ratings": [103, 53, 95], "rankings": [3, 1, 2], "batch": 2, "ratingTime": 29797, "groundtruth": [61, 65, 70], "frames": 3, "rankingTime": 9700}, {"ratings": [75, 75, 85, 95, 103, 96], "rankings": [5, 4, 2, 1, 3, 6], "batch": 5, "ratingTime": 45891, "groundtruth": [56, 58, 71, 74, 76, 78], "frames": 6, "rankingTime": 7570}, {"ratings": [65, 76, 86, 75, 98], "rankings": [4, 2, 3, 1, 5], "batch": 4, "ratingTime": 22732, "groundtruth": [58, 62, 66, 68, 70], "frames": 5, "rankingTime": 5392}, {"ratings": [45, 102], "rankings": [1, 2], "batch": 1, "ratingTime": 9357, "groundtruth": [52, 67], "frames": 2, "rankingTime": 4049}, {"ratings": [50, 60, 70, 80, 90], "rankings": [5, 3, 2, 4, 1], "batch": 5, "ratingTime": 16234, "groundtruth": [51, 55, 58, 64, 67], "frames": 5, "rankingTime": 14331}, {"ratings": [50, 90], "rankings": [2, 1], "batch": 2, "ratingTime": 2969, "groundtruth": [53, 73], "frames": 2, "rankingTime": 5094}, {"ratings": [120, 100, 50, 80, 90, 110], "rankings": [2, 3, 4, 5, 1, 6], "batch": 6, "ratingTime": 8460, "groundtruth": [57, 58, 59, 63, 67, 69], "frames": 6, "rankingTime": 8208}, {"ratings": [70, 60, 90], "rankings": [3, 2, 1], "batch": 3, "ratingTime": 4240, "groundtruth": [50, 70, 79], "frames": 3, "rankingTime": 3375}, {"ratings": [45, 60], "rankings": [2, 1], "batch": 2, "ratingTime": 33639, "groundtruth": [50, 77], "frames": 2, "rankingTime": 9142}, {"ratings": [60, 65, 60, 45, 50, 55], "rankings": [5, 6, 4, 3, 1, 2], "batch": 6, "ratingTime": 35286, "groundtruth": [51, 52, 61, 65, 75, 76], "frames": 6, "rankingTime": 77567}, {"ratings": [60, 55, 50], "rankings": [3, 1, 2], "batch": 3, "ratingTime": 21358, "groundtruth": [61, 71, 72], "frames": 3, "rankingTime": 22082}, {"ratings": [45, 52, 48, 40, 50], "rankings": [5, 4, 2, 1, 3], "batch": 5, "ratingTime": 20733, "groundtruth": [63, 65, 70, 73, 77], "frames": 5, "rankingTime": 49129}, {"ratings": [67, 82, 102], "rankings": [3, 2, 1], "batch": 0, "ratingTime": 58936, "groundtruth": [51, 63, 66], "frames": 3, "rankingTime": 34914}, {"ratings": [75, 104], "rankings": [1, 2], "batch": 0, "ratingTime": 16079, "groundtruth": [53, 70], "frames": 2, "rankingTime": 6545}, {"ratings": [79, 97, 82, 167, 120, 125], "rankings": [1, 3, 2, 5, 4, 6], "batch": 1, "ratingTime": 60288, "groundtruth": [55, 62, 63, 71, 76, 79], "frames": 6, "rankingTime": 9844}, {"ratings": [76, 109, 120, 154, 167], "rankings": [4, 5, 2, 3, 1], "batch": 0, "ratingTime": 48358, "groundtruth": [55, 57, 64, 67, 76], "frames": 5, "rankingTime": 18730}, {"ratings": [55, 68, 73, 63, 60], "rankings": [5, 3, 4, 2, 1], "batch": 1, "ratingTime": 69898, "groundtruth": [54, 56, 58, 60, 68], "frames": 5, "rankingTime": 116031}, {"ratings": [60, 80, 70], "rankings": [3, 1, 2], "batch": 0, "ratingTime": 37772, "groundtruth": [58, 74, 77], "frames": 3, "rankingTime": 24139}, {"ratings": [75, 80], "rankings": [2, 1], "batch": 0, "ratingTime": 21021, "groundtruth": [68, 75], "frames": 2, "rankingTime": 17403}, {"ratings": [60, 70, 63, 75, 79, 80], "rankings": [6, 4, 5, 3, 2, 1], "batch": 1, "ratingTime": 81164, "groundtruth": [51, 53, 54, 66, 68, 69], "frames": 6, "rankingTime": 88368}, {"ratings": [45, 35, 45], "rankings": [1, 2, 3], "batch": 1, "ratingTime": 10706, "groundtruth": [52, 61, 72], "frames": 3, "rankingTime": 4926}, {"ratings": [45, 35, 45, 45, 55, 45], "rankings": [1, 5, 2, 4, 6, 3], "batch": 3, "ratingTime": 25135, "groundtruth": [60, 62, 65, 69, 70, 75], "frames": 6, "rankingTime": 3916}, {"ratings": [35, 55], "rankings": [2, 1], "batch": 1, "ratingTime": 5873, "groundtruth": [65, 68], "frames": 2, "rankingTime": 3204}, {"ratings": [25, 35, 30, 35, 40], "rankings": [4, 5, 2, 3, 1], "batch": 3, "ratingTime": 13295, "groundtruth": [54, 55, 56, 58, 68], "frames": 5, "rankingTime": 4565}, {"ratings": [70, 50, 70], "rankings": [3, 1, 2], "batch": 3, "ratingTime": 28792, "groundtruth": [60, 69, 74], "frames": 3, "rankingTime": 135461}, {"ratings": [40, 60], "rankings": [2, 1], "batch": 2, "ratingTime": 29311, "groundtruth": [54, 62], "frames": 2, "rankingTime": 879515}, {"ratings": [60, 50, 40, 50, 70], "rankings": [5, 3, 4, 2, 1], "batch": 6, "ratingTime": 40428, "groundtruth": [52, 53, 54, 59, 69], "frames": 5, "rankingTime": 16369}, {"ratings": [50, 70, 60, 80, 76, 70], "rankings": [6, 3, 5, 4, 1, 2], "batch": 7, "ratingTime": 38469, "groundtruth": [50, 61, 64, 68, 74, 77], "frames": 6, "rankingTime": 24668}, {"ratings": [63, 69, 73], "rankings": [3, 2, 1], "batch": 4, "ratingTime": 63923, "groundtruth": [63, 69, 73], "frames": 3, "rankingTime": 11395}, {"ratings": [50, 61, 73, 75, 76], "rankings": [5, 4, 3, 2, 1], "batch": 6, "ratingTime": 28450, "groundtruth": [50, 61, 73, 75, 76], "frames": 5, "rankingTime": 26803}, {"ratings": [61, 64, 66, 69, 74, 77], "rankings": [6, 5, 4, 3, 2, 1], "batch": 8, "ratingTime": 14837, "groundtruth": [61, 64, 66, 69, 74, 77], "frames": 6, "rankingTime": 56676}, {"ratings": [59, 68], "rankings": [2, 1], "batch": 2, "ratingTime": 6723, "groundtruth": [59, 68], "frames": 2, "rankingTime": 6522}, {"ratings": [55, 50, 56, 55, 50], "rankings": [1, 4, 5, 2, 3], "batch": 6, "ratingTime": 41215, "groundtruth": [57, 64, 66, 77, 79], "frames": 5, "rankingTime": 29133}, {"ratings": [55, 57, 50], "rankings": [3, 1, 2], "batch": 4, "ratingTime": 9538, "groundtruth": [50, 51, 68], "frames": 3, "rankingTime": 14169}, {"ratings": [53, 40, 45, 50, 55, 57], "rankings": [5, 6, 2, 3, 4, 1], "batch": 8, "ratingTime": 27541, "groundtruth": [51, 54, 55, 56, 63, 70], "frames": 6, "rankingTime": 15572}, {"ratings": [55, 60], "rankings": [1, 2], "batch": 2, "ratingTime": 7768, "groundtruth": [72, 75], "frames": 2, "rankingTime": 11521}, {"ratings": [70, 50, 75, 59, 67, 40], "rankings": [1, 3, 2, 4, 5, 6], "batch": 8, "ratingTime": 56883, "groundtruth": [53, 62, 71, 73, 78, 79], "frames": 6, "rankingTime": 8492}, {"ratings": [30, 50, 60], "rankings": [3, 2, 1], "batch": 4, "ratingTime": 17003, "groundtruth": [53, 55, 57], "frames": 3, "rankingTime": 14705}, {"ratings": [40, 50], "rankings": [2, 1], "batch": 2, "ratingTime": 14634, "groundtruth": [56, 74], "frames": 2, "rankingTime": 5190}, {"ratings": [30, 46, 75, 66, 50], "rankings": [5, 3, 4, 2, 1], "batch": 7, "ratingTime": 30469, "groundtruth": [50, 51, 56, 57, 67], "frames": 5, "rankingTime": 9293}, {"ratings": [96, 85, 70], "rankings": [3, 2, 1], "batch": 4, "ratingTime": 34096, "groundtruth": [61, 64, 76], "frames": 3, "rankingTime": 64421}, {"ratings": [77, 60], "rankings": [2, 1], "batch": 2, "ratingTime": 17508, "groundtruth": [60, 65], "frames": 2, "rankingTime": 10821}, {"ratings": [93, 84, 88, 80, 96], "rankings": [5, 2, 4, 3, 1], "batch": 7, "ratingTime": 38791, "groundtruth": [66, 70, 71, 76, 77], "frames": 5, "rankingTime": 20825}, {"ratings": [63, 55, 62, 57, 72, 77], "rankings": [6, 4, 5, 2, 3, 1], "batch": 8, "ratingTime": 57337, "groundtruth": [52, 59, 60, 67, 72, 75], "frames": 6, "rankingTime": 21191}, {"ratings": [80, 120, 100], "rankings": [3, 2, 1], "batch": 4, "ratingTime": 45347, "groundtruth": [52, 71, 79], "frames": 3, "rankingTime": 28145}, {"ratings": [60, 50, 80, 100, 90], "rankings": [5, 4, 2, 3, 1], "batch": 7, "ratingTime": 63615, "groundtruth": [52, 60, 61, 68, 69], "frames": 5, "rankingTime": 35885}, {"ratings": [60, 80, 70, 75, 85, 80], "rankings": [6, 5, 3, 4, 2, 1], "batch": 9, "ratingTime": 102289, "groundtruth": [60, 68, 72, 74, 75, 77], "frames": 6, "rankingTime": 31310}, {"ratings": [80, 80], "rankings": [1, 2], "batch": 3, "ratingTime": 22187, "groundtruth": [67, 68], "frames": 2, "rankingTime": 19696}, {"ratings": [62, 67], "rankings": [2, 1], "batch": 3, "ratingTime": 27187, "groundtruth": [69, 77], "frames": 2, "rankingTime": 10571}, {"ratings": [45, 53, 57, 45, 59], "rankings": [2, 3, 5, 4, 1], "batch": 7, "ratingTime": 21966, "groundtruth": [54, 59, 64, 73, 79], "frames": 5, "rankingTime": 15104}, {"ratings": [40, 52, 45, 56, 63, 46], "rankings": [6, 4, 5, 2, 3, 1], "batch": 9, "ratingTime": 23448, "groundtruth": [53, 61, 63, 71, 73, 79], "frames": 6, "rankingTime": 11502}, {"ratings": [47, 46, 53], "rankings": [3, 2, 1], "batch": 4, "ratingTime": 13294, "groundtruth": [56, 62, 72], "frames": 3, "rankingTime": 6006}, {"ratings": [55, 45, 50, 58, 30, 65], "rankings": [2, 4, 6, 3, 5, 1], "batch": 9, "ratingTime": 41824, "groundtruth": [50, 54, 56, 57, 58, 64], "frames": 6, "rankingTime": 22462}, {"ratings": [60, 65, 59], "rankings": [3, 2, 1], "batch": 4, "ratingTime": 13781, "groundtruth": [54, 59, 65], "frames": 3, "rankingTime": 13160}, {"ratings": [55, 65, 45, 60, 65], "rankings": [5, 1, 4, 3, 2], "batch": 7, "ratingTime": 21105, "groundtruth": [55, 63, 65, 72, 78], "frames": 5, "rankingTime": 11603}, {"ratings": [45, 55], "rankings": [2, 1], "batch": 3, "ratingTime": 11595, "groundtruth": [56, 73], "frames": 2, "rankingTime": 6927}, {"ratings": [40, 45], "rankings": [1, 2], "batch": 0, "ratingTime": 11844, "groundtruth": [56, 58], "frames": 2, "rankingTime": 10002}, {"ratings": [53, 47, 45, 49, 51], "rankings": [5, 2, 4, 1, 3], "batch": 0, "ratingTime": 13607, "groundtruth": [52, 60, 62, 63, 73], "frames": 5, "rankingTime": 11698}, {"ratings": [30, 33, 36], "rankings": [3, 2, 1], "batch": 0, "ratingTime": 9731, "groundtruth": [54, 61, 67], "frames": 3, "rankingTime": 5955}, {"ratings": [41, 50, 35, 44, 38, 47], "rankings": [6, 1, 5, 2, 4, 3], "batch": 0, "ratingTime": 19302, "groundtruth": [61, 64, 69, 70, 71, 73], "frames": 6, "rankingTime": 14060}, {"ratings": [60, 80, 75, 105, 90], "rankings": [5, 3, 4, 2, 1], "batch": 0, "ratingTime": 120835, "groundtruth": [53, 71, 74, 78, 79], "frames": 5, "rankingTime": 81840}, {"ratings": [60, 70], "rankings": [2, 1], "batch": 0, "ratingTime": 23447, "groundtruth": [60, 74], "frames": 2, "rankingTime": 11951}, {"ratings": [55, 70, 55, 50, 65, 100], "rankings": [6, 3, 2, 5, 4, 1], "batch": 0, "ratingTime": 75243, "groundtruth": [51, 54, 56, 59, 60, 76], "frames": 6, "rankingTime": 17989}, {"ratings": [60, 55, 80], "rankings": [3, 2, 1], "batch": 0, "ratingTime": 47930, "groundtruth": [55, 60, 79], "frames": 3, "rankingTime": 11356}, {"ratings": [50, 65, 62, 70, 60], "rankings": [4, 3, 5, 1, 2], "batch": 4, "ratingTime": 21808, "groundtruth": [50, 51, 54, 72, 78], "frames": 5, "rankingTime": 11359}, {"ratings": [66, 70, 77, 60, 55, 80], "rankings": [5, 3, 4, 6, 1, 2], "batch": 5, "ratingTime": 16379, "groundtruth": [59, 60, 62, 67, 68, 77], "frames": 6, "rankingTime": 7285}, {"ratings": [55, 67], "rankings": [1, 2], "batch": 1, "ratingTime": 6144, "groundtruth": [57, 73], "frames": 2, "rankingTime": 4004}, {"ratings": [56, 61, 70], "rankings": [2, 3, 1], "batch": 2, "ratingTime": 8895, "groundtruth": [54, 57, 74], "frames": 3, "rankingTime": 5166}, {"ratings": [40, 50, 75, 70, 60, 75], "rankings": [6, 1, 5, 3, 4, 2], "batch": 7, "ratingTime": 145557, "groundtruth": [55, 67, 69, 71, 75, 76], "frames": 6, "rankingTime": 45316}, {"ratings": [50, 65], "rankings": [1, 2], "batch": 2, "ratingTime": 10880, "groundtruth": [57, 64], "frames": 2, "rankingTime": 9861}, {"ratings": [40, 50, 70], "rankings": [3, 2, 1], "batch": 3, "ratingTime": 44340, "groundtruth": [53, 63, 78], "frames": 3, "rankingTime": 7797}, {"ratings": [55, 50, 65, 75, 75], "rankings": [5, 4, 3, 2, 1], "batch": 6, "ratingTime": 42518, "groundtruth": [62, 63, 67, 74, 78], "frames": 5, "rankingTime": 14394}, {"ratings": [56, 60, 50, 45, 50], "rankings": [2, 5, 4, 3, 1], "batch": 5, "ratingTime": 19176, "groundtruth": [52, 66, 75, 76, 79], "frames": 5, "rankingTime": 16340}, {"ratings": [50, 43, 50, 40, 48, 45], "rankings": [6, 2, 4, 5, 3, 1], "batch": 6, "ratingTime": 20903, "groundtruth": [50, 56, 62, 66, 74, 78], "frames": 6, "rankingTime": 9168}, {"ratings": [30, 40], "rankings": [2, 1], "batch": 2, "ratingTime": 6449, "groundtruth": [51, 70], "frames": 2, "rankingTime": 7866}, {"ratings": [45, 40, 40], "rankings": [2, 3, 1], "batch": 3, "ratingTime": 15132, "groundtruth": [51, 57, 73], "frames": 3, "rankingTime": 5954}, {"ratings": [98, 60, 70, 110, 90], "rankings": [3, 5, 2, 1, 4], "batch": 7, "ratingTime": 61000, "groundtruth": [53, 58, 62, 74, 75], "frames": 5, "rankingTime": 19687}, {"ratings": [68, 80], "rankings": [2, 1], "batch": 2, "ratingTime": 18573, "groundtruth": [52, 63], "frames": 2, "rankingTime": 15152}, {"ratings": [78, 120, 90], "rankings": [3, 2, 1], "batch": 4, "ratingTime": 31680, "groundtruth": [58, 67, 77], "frames": 3, "rankingTime": 8994}, {"ratings": [76, 80, 80, 86, 76, 87], "rankings": [5, 6, 4, 2, 1, 3], "batch": 8, "ratingTime": 60682, "groundtruth": [50, 57, 58, 65, 68, 76], "frames": 6, "rankingTime": 13897}, {"ratings": [50, 64, 53, 57, 60, 65], "rankings": [3, 6, 4, 5, 1, 2], "batch": 11, "ratingTime": 98521, "groundtruth": [50, 57, 58, 60, 67, 75], "frames": 6, "rankingTime": 18412}, {"ratings": [42, 53, 52, 50, 55], "rankings": [5, 3, 4, 1, 2], "batch": 9, "ratingTime": 83118, "groundtruth": [55, 58, 59, 65, 71], "frames": 5, "rankingTime": 12870}, {"ratings": [48, 60], "rankings": [2, 1], "batch": 3, "ratingTime": 39948, "groundtruth": [51, 61], "frames": 2, "rankingTime": 9319}, {"ratings": [48, 70, 80], "rankings": [2, 3, 1], "batch": 5, "ratingTime": 43067, "groundtruth": [57, 60, 73], "frames": 3, "rankingTime": 7856}, {"ratings": [30, 40, 40, 35, 35, 50], "rankings": [6, 5, 4, 3, 1, 2], "batch": 11, "ratingTime": 30198, "groundtruth": [54, 59, 64, 70, 74, 77], "frames": 6, "rankingTime": 25318}, {"ratings": [35, 45, 40], "rankings": [2, 3, 1], "batch": 5, "ratingTime": 13568, "groundtruth": [66, 68, 74], "frames": 3, "rankingTime": 15696}, {"ratings": [38, 48, 50, 44, 35], "rankings": [5, 4, 3, 2, 1], "batch": 9, "ratingTime": 15816, "groundtruth": [61, 63, 68, 73, 77], "frames": 5, "rankingTime": 16047}, {"ratings": [30, 35], "rankings": [1, 2], "batch": 3, "ratingTime": 7949, "groundtruth": [55, 78], "frames": 2, "rankingTime": 5161}, {"ratings": [60, 60], "rankings": [2, 1], "batch": 3, "ratingTime": 23120, "groundtruth": [64, 72], "frames": 2, "rankingTime": 7708}, {"ratings": [60, 60, 80, 60, 80], "rankings": [4, 5, 3, 2, 1], "batch": 9, "ratingTime": 24083, "groundtruth": [52, 53, 69, 72, 79], "frames": 5, "rankingTime": 15557}, {"ratings": [60, 70, 80], "rankings": [2, 3, 1], "batch": 5, "ratingTime": 16958, "groundtruth": [59, 61, 63], "frames": 3, "rankingTime": 27090}, {"ratings": [80, 60, 50, 60, 80, 70], "rankings": [6, 5, 3, 2, 4, 1], "batch": 11, "ratingTime": 32627, "groundtruth": [51, 55, 61, 63, 68, 76], "frames": 6, "rankingTime": 24127}, {"ratings": [50, 60, 55], "rankings": [2, 3, 1], "batch": 5, "ratingTime": 30389, "groundtruth": [51, 53, 62], "frames": 3, "rankingTime": 31365}, {"ratings": [45, 50, 55, 60, 65], "rankings": [5, 4, 3, 2, 1], "batch": 9, "ratingTime": 58780, "groundtruth": [57, 66, 74, 75, 78], "frames": 5, "rankingTime": 32536}, {"ratings": [57, 54, 65, 69, 70, 67], "rankings": [4, 6, 5, 3, 2, 1], "batch": 11, "ratingTime": 149458, "groundtruth": [52, 56, 62, 71, 78, 79], "frames": 6, "rankingTime": 26523}, {"ratings": [69, 75], "rankings": [2, 1], "batch": 3, "ratingTime": 44792, "groundtruth": [70, 76], "frames": 2, "rankingTime": 24642}, {"ratings": [60, 70, 82], "rankings": [2, 3, 1], "batch": 5, "ratingTime": 20704, "groundtruth": [55, 56, 64], "frames": 3, "rankingTime": 29218}, {"ratings": [55, 69, 70, 66, 66, 65], "rankings": [5, 6, 4, 2, 3, 1], "batch": 10, "ratingTime": 92046, "groundtruth": [52, 63, 75, 76, 77, 79], "frames": 6, "rankingTime": 19276}, {"ratings": [69, 66, 64, 75, 75], "rankings": [3, 5, 4, 2, 1], "batch": 8, "ratingTime": 28222, "groundtruth": [51, 54, 56, 75, 78], "frames": 5, "rankingTime": 16370}, {"ratings": [64, 75], "rankings": [2, 1], "batch": 3, "ratingTime": 11719, "groundtruth": [53, 75], "frames": 2, "rankingTime": 6497}, {"ratings": [45, 35, 50, 67, 65], "rankings": [4, 5, 3, 1, 2], "batch": 8, "ratingTime": 89211, "groundtruth": [52, 57, 61, 73, 74], "frames": 5, "rankingTime": 50302}, {"ratings": [42, 37, 30, 50, 58, 58], "rankings": [5, 6, 3, 2, 4, 1], "batch": 10, "ratingTime": 87311, "groundtruth": [54, 57, 61, 64, 71, 78], "frames": 6, "rankingTime": 27819}, {"ratings": [40, 52], "rankings": [2, 1], "batch": 3, "ratingTime": 15625, "groundtruth": [50, 66], "frames": 2, "rankingTime": 8389}, {"ratings": [45, 53, 68], "rankings": [3, 2, 1], "batch": 5, "ratingTime": 58478, "groundtruth": [58, 69, 75], "frames": 3, "rankingTime": 13267}, {"ratings": [78, 65, 99], "rankings": [3, 2, 1], "batch": 5, "ratingTime": 38139, "groundtruth": [50, 54, 78], "frames": 3, "rankingTime": 21288}, {"ratings": [60, 65, 80, 70, 60, 70], "rankings": [4, 6, 5, 2, 3, 1], "batch": 10, "ratingTime": 70015, "groundtruth": [55, 58, 60, 67, 68, 70], "frames": 6, "rankingTime": 28115}, {"ratings": [70, 65], "rankings": [2, 1], "batch": 3, "ratingTime": 23439, "groundtruth": [54, 58], "frames": 2, "rankingTime": 22296}, {"ratings": [70, 70, 65, 75, 90], "rankings": [4, 5, 2, 3, 1], "batch": 8, "ratingTime": 61494, "groundtruth": [60, 62, 70, 77, 79], "frames": 5, "rankingTime": 22752}, {"ratings": [60, 70, 49, 57, 55, 60], "rankings": [5, 2, 6, 4, 1, 3], "batch": 6, "ratingTime": 83530, "groundtruth": [53, 54, 55, 70, 73, 79], "frames": 6, "rankingTime": 36984}, {"ratings": [50, 60, 68], "rankings": [3, 2, 1], "batch": 3, "ratingTime": 31756, "groundtruth": [56, 66, 75], "frames": 3, "rankingTime": 15604}, {"ratings": [35, 55, 50, 46, 60], "rankings": [2, 4, 5, 3, 1], "batch": 5, "ratingTime": 35962, "groundtruth": [50, 53, 59, 60, 62], "frames": 5, "rankingTime": 27695}, {"ratings": [45, 60], "rankings": [2, 1], "batch": 2, "ratingTime": 11848, "groundtruth": [55, 67], "frames": 2, "rankingTime": 10884}, {"ratings": [48, 37, 53, 36, 68], "rankings": [5, 4, 2, 3, 1], "batch": 5, "ratingTime": 148602, "groundtruth": [57, 61, 68, 69, 78], "frames": 5, "rankingTime": 55236}, {"ratings": [46, 53, 39, 61, 48, 69], "rankings": [5, 4, 6, 3, 2, 1], "batch": 7, "ratingTime": 144728, "groundtruth": [52, 54, 58, 59, 72, 78], "frames": 6, "rankingTime": 260837}, {"ratings": [39, 65, 52], "rankings": [3, 2, 1], "batch": 3, "ratingTime": 52413, "groundtruth": [54, 62, 68], "frames": 3, "rankingTime": 10798}, {"ratings": [42, 62], "rankings": [2, 1], "batch": 2, "ratingTime": 29859, "groundtruth": [71, 79], "frames": 2, "rankingTime": 7965}, {"ratings": [32, 32, 29, 35, 30, 30], "rankings": [3, 1, 2, 5, 4, 6], "batch": 10, "ratingTime": 32758, "groundtruth": [50, 51, 53, 56, 59, 74], "frames": 6, "rankingTime": 15731}, {"ratings": [35, 25, 38, 35, 40], "rankings": [1, 4, 2, 3, 5], "batch": 8, "ratingTime": 14075, "groundtruth": [50, 53, 59, 63, 72], "frames": 5, "rankingTime": 9445}, {"ratings": [30, 38, 40], "rankings": [1, 2, 3], "batch": 5, "ratingTime": 9889, "groundtruth": [67, 72, 76], "frames": 3, "rankingTime": 6003}, {"ratings": [37, 40], "rankings": [2, 1], "batch": 3, "ratingTime": 6056, "groundtruth": [71, 79], "frames": 2, "rankingTime": 4619}, {"ratings": [50, 40, 35, 40, 60], "rankings": [5, 3, 4, 1, 2], "batch": 9, "ratingTime": 18453, "groundtruth": [50, 54, 56, 67, 70], "frames": 5, "rankingTime": 23937}, {"ratings": [40, 50, 65], "rankings": [3, 2, 1], "batch": 5, "ratingTime": 6407, "groundtruth": [65, 77, 79], "frames": 3, "rankingTime": 6032}, {"ratings": [50, 40], "rankings": [2, 1], "batch": 3, "ratingTime": 3577, "groundtruth": [57, 60], "frames": 2, "rankingTime": 3193}, {"ratings": [35, 40, 40, 55, 45, 60], "rankings": [6, 5, 4, 2, 1, 3], "batch": 10, "ratingTime": 14504, "groundtruth": [62, 65, 66, 69, 72, 73], "frames": 6, "rankingTime": 19778}, {"ratings": [32, 35, 42, 45, 40, 55], "rankings": [6, 4, 3, 5, 2, 1], "batch": 7, "ratingTime": 128855, "groundtruth": [51, 53, 56, 57, 60, 70], "frames": 6, "rankingTime": 101858}, {"ratings": [38, 33], "rankings": [1, 2], "batch": 2, "ratingTime": 70246, "groundtruth": [58, 61], "frames": 2, "rankingTime": 24561}, {"ratings": [33, 37, 46, 42, 56], "rankings": [5, 4, 3, 2, 1], "batch": 6, "ratingTime": 337912, "groundtruth": [55, 56, 68, 70, 71], "frames": 5, "rankingTime": 99881}, {"ratings": [31, 48, 54], "rankings": [3, 2, 1], "batch": 3, "ratingTime": 98509, "groundtruth": [64, 76, 77], "frames": 3, "rankingTime": 37556}, {"ratings": [35, 28, 25, 38, 40, 45], "rankings": [6, 5, 4, 2, 3, 1], "batch": 9, "ratingTime": 82047, "groundtruth": [52, 62, 67, 69, 76, 78], "frames": 6, "rankingTime": 36229}, {"ratings": [40, 45, 60, 50, 45], "rankings": [5, 4, 3, 2, 1], "batch": 8, "ratingTime": 30252, "groundtruth": [58, 64, 65, 66, 69], "frames": 5, "rankingTime": 14791}, {"ratings": [35, 36], "rankings": [2, 1], "batch": 3, "ratingTime": 60930, "groundtruth": [52, 74], "frames": 2, "rankingTime": 6382}, {"ratings": [49, 44, 55], "rankings": [2, 3, 1], "batch": 4, "ratingTime": 11849, "groundtruth": [66, 70, 74], "frames": 3, "rankingTime": 7975}, {"ratings": [85, 100], "rankings": [2, 1], "batch": 3, "ratingTime": 29885, "groundtruth": [62, 65], "frames": 2, "rankingTime": 31811}, {"ratings": [60, 75, 66], "rankings": [3, 1, 2], "batch": 4, "ratingTime": 32287, "groundtruth": [60, 75, 78], "frames": 3, "rankingTime": 12481}, {"ratings": [55, 82, 44, 78, 85], "rankings": [5, 3, 1, 2, 4], "batch": 8, "ratingTime": 40622, "groundtruth": [55, 67, 68, 71, 76], "frames": 5, "rankingTime": 16760}, {"ratings": [48, 40, 48, 50, 88, 38], "rankings": [5, 6, 2, 4, 1, 3], "batch": 9, "ratingTime": 32033, "groundtruth": [51, 55, 59, 65, 66, 70], "frames": 6, "rankingTime": 31566}, {"ratings": [61, 76, 80], "rankings": [3, 2, 1], "batch": 2, "ratingTime": 68257, "groundtruth": [60, 73, 79], "frames": 3, "rankingTime": 11706}, {"ratings": [70, 65, 80, 70, 60], "rankings": [5, 4, 1, 3, 2], "batch": 4, "ratingTime": 21053, "groundtruth": [63, 64, 74, 75, 76], "frames": 5, "rankingTime": 11122}, {"ratings": [60, 65], "rankings": [2, 1], "batch": 1, "ratingTime": 10253, "groundtruth": [54, 60], "frames": 2, "rankingTime": 4555}, {"ratings": [70, 60, 80, 70, 65, 70], "rankings": [6, 2, 5, 4, 3, 1], "batch": 5, "ratingTime": 24291, "groundtruth": [54, 63, 70, 73, 75, 79], "frames": 6, "rankingTime": 9379}, {"ratings": [50, 65, 45, 50, 55], "rankings": [5, 3, 4, 1, 2], "batch": 6, "ratingTime": 65014, "groundtruth": [51, 58, 60, 65, 72], "frames": 5, "rankingTime": 46913}, {"ratings": [70, 90], "rankings": [2, 1], "batch": 2, "ratingTime": 22414, "groundtruth": [66, 78], "frames": 2, "rankingTime": 16103}, {"ratings": [55, 90, 60, 70, 90, 100], "rankings": [3, 4, 6, 5, 2, 1], "batch": 7, "ratingTime": 34679, "groundtruth": [62, 63, 65, 66, 73, 79], "frames": 6, "rankingTime": 13425}, {"ratings": [55, 65, 70], "rankings": [3, 2, 1], "batch": 3, "ratingTime": 14586, "groundtruth": [52, 65, 67], "frames": 3, "rankingTime": 10031}, {"ratings": [50, 60, 80], "rankings": [3, 2, 1], "batch": 3, "ratingTime": 43039, "groundtruth": [55, 58, 59], "frames": 3, "rankingTime": 25937}, {"ratings": [65, 60], "rankings": [2, 1], "batch": 2, "ratingTime": 10484, "groundtruth": [69, 76], "frames": 2, "rankingTime": 11553}, {"ratings": [65, 60, 70, 70, 75], "rankings": [5, 4, 1, 3, 2], "batch": 5, "ratingTime": 48965, "groundtruth": [54, 56, 71, 72, 74], "frames": 5, "rankingTime": 13272}, {"ratings": [71, 85, 65, 80, 70, 75], "rankings": [6, 5, 3, 4, 1, 2], "batch": 6, "ratingTime": 43686, "groundtruth": [60, 64, 68, 71, 72, 77], "frames": 6, "rankingTime": 29204}, {"ratings": [125, 120, 110, 105, 150, 90], "rankings": [1, 6, 5, 3, 2, 4], "batch": 11, "ratingTime": 123146, "groundtruth": [53, 65, 66, 69, 72, 73], "frames": 6, "rankingTime": 36017}, {"ratings": [110, 120], "rankings": [1, 2], "batch": 3, "ratingTime": 13442, "groundtruth": [59, 63], "frames": 2, "rankingTime": 13077}, {"ratings": [150, 120, 100], "rankings": [2, 1, 3], "batch": 5, "ratingTime": 16981, "groundtruth": [52, 70, 71], "frames": 3, "rankingTime": 7885}, {"ratings": [100, 100, 110, 120, 105], "rankings": [1, 5, 2, 3, 4], "batch": 9, "ratingTime": 42503, "groundtruth": [51, 60, 62, 64, 76], "frames": 5, "rankingTime": 22657}]